nipcat/__init__.py
nipcat/cli.py
nipcat/domain/__init__.py
nipcat/domain/main.py
nipcat/domain/types.py
nipcat/network/__init__.py
nipcat/network/main.py
nipcat/network/types.py
nipcat-0.2.0.dist-info/METADATA
nipcat-0.2.0.dist-info/WHEEL
nipcat-0.2.0.dist-info/entry_points.txt
nipcat-0.2.0.dist-info/RECORD
