Metadata-Version: 2.1
Name: nipcat
Version: 0.2.0
Summary: ip calculator
Author: walidsa3d
Requires-Python: >=3.10,<4.0
Classifier: Programming Language :: Python :: 3
Classifier: Programming Language :: Python :: 3.10
Classifier: Programming Language :: Python :: 3.11
Classifier: Programming Language :: Python :: 3.12
Classifier: Programming Language :: Python :: 3.13
Requires-Dist: click (>=8.1.3,<9.0.0)
Requires-Dist: dnspython (>=2.7.0,<3.0.0)
Requires-Dist: netifaces (>=0.11.0,<0.12.0)
Requires-Dist: pytest (>=8.3.3,<9.0.0)
Requires-Dist: pytest-mock (>=3.14.0,<4.0.0)
Requires-Dist: python-whois (>=0.9.5,<0.10.0)
Requires-Dist: rich (>=13.9.4,<14.0.0)
